automa_ai/__init__.py
automa_ai/agent_test/adk_agent_test.py
automa_ai/agent_test/react_agent_test.py
automa_ai/agents/__init__.py
automa_ai/agents/adk_agent.py
automa_ai/agents/agent_factory.py
automa_ai/agents/langgraph_chatagent.py
automa_ai/agents/orchestrator_local_agent.py
automa_ai/agents/orchestrator_network_agent.py
automa_ai/agents/react_langgraph_agent.py
automa_ai/agents/remote_agent.py
automa_ai/client/__init__.py
automa_ai/client/simple_client.py
automa_ai/client/ui_util.py
automa_ai/common/__init__.py
automa_ai/common/agent_executor.py
automa_ai/common/agent_registry.py
automa_ai/common/agent_runner.py
automa_ai/common/base_agent.py
automa_ai/common/chunk.py
automa_ai/common/chunk_test.py
automa_ai/common/file_util.py
automa_ai/common/mcp_registry.py
automa_ai/common/prompts.py
automa_ai/common/push_notification_auth.py
automa_ai/common/response_parser.py
automa_ai/common/response_parser_test.py
automa_ai/common/retriever.py
automa_ai/common/setup_logging.py
automa_ai/common/types.py
automa_ai/common/utils.py
automa_ai/common/workflow.py
automa_ai/mcp_servers/__init__.py
automa_ai/mcp_servers/agent_card_server.py
automa_ai/mcp_servers/client.py
automa_ai/mcp_servers/mcp_test.py
automa_ai/mcp_servers/server.py
automa_ai/mcp_servers/test_agent_card_matching.py
automa_ai/mcp_servers/test_cases.json
automa_ai/mcp_servers/eplus_doc/README.md
automa_ai/mcp_servers/eplus_doc/eplus_doc_client.py
automa_ai/mcp_servers/eplus_doc/eplus_doc_mcp_test.py
automa_ai/mcp_servers/eplus_doc/eplus_doc_server.py
automa_ai/mcp_servers/eplus_doc/requirements.txt
automa_ai/metrics/__init__.py
automa_ai/metrics/collector.py
automa_ai/metrics/eval_pipeline.py
automa_ai/metrics/extractor.py
automa_ai/network/__init__.py
automa_ai/network/agentic_network.py
automa_ai/network/chat_network.py
automa_ai/prompt_engineering/__init__.py
automa_ai-0.3.1.dist-info/METADATA
automa_ai-0.3.1.dist-info/WHEEL
automa_ai-0.3.1.dist-info/licenses/LICENSE.md
automa_ai-0.3.1.dist-info/RECORD
