Metadata-Version: 2.4
Name: automa_ai
Version: 0.3.1
Summary: PNNL Auto Multi-Agent AI: Dynamic multi-agent system for building applications
Author-email: Weili Xu <weili.xu@pnnl.gov>, "Hanlong, Wan" <hanlong.wan@pnnl.gov>
License-Expression: BSD-2-Clause
License-File: LICENSE.md
Requires-Python: >=3.12
Requires-Dist: a2a-sdk>=0.3.10
Requires-Dist: asyncclick>=8.3.0.7
Requires-Dist: bs4>=0.0.2
Requires-Dist: chromadb>=1.2.2
Requires-Dist: deepeval>=3.7.2
Requires-Dist: google-adk>=1.17.0
Requires-Dist: google-genai>=1.46.0
Requires-Dist: httpx>=0.28.1
Requires-Dist: jwcrypto>=1.5.6
Requires-Dist: langchain-anthropic>=1.0.0
Requires-Dist: langchain-aws>=1.1.0
Requires-Dist: langchain-chroma>=1.0.0
Requires-Dist: langchain-community>=0.4.1
Requires-Dist: langchain-google-genai>=3.2.0
Requires-Dist: langchain-huggingface>=1.0.1
Requires-Dist: langchain-mcp-adapters>=0.1.11
Requires-Dist: langchain-ollama>=1.0.0
Requires-Dist: langchain-openai>=1.0.1
Requires-Dist: langchain>=1.0.2
Requires-Dist: langgraph>=1.0.1
Requires-Dist: litellm>=1.79.0
Requires-Dist: multiprocessing-logging>=0.3.4
Requires-Dist: networkx>=3.5
Requires-Dist: pandas-stubs==2.3.3.251219
Requires-Dist: pandas>=2.3.3
Requires-Dist: pydantic>=2.12.3
Requires-Dist: pyjwt>=2.10.1
Requires-Dist: streamlit>=1.51.0
Requires-Dist: uvicorn>=0.38.0
Provides-Extra: eplus-mcp-demo
Requires-Dist: eppy>=0.5.63; extra == 'eplus-mcp-demo'
Requires-Dist: matplotlib>=3.10.7; extra == 'eplus-mcp-demo'
Requires-Dist: plotly>=6.4.0; extra == 'eplus-mcp-demo'
Provides-Extra: sim-bem-network
Requires-Dist: openstudio>=3.10.0; extra == 'sim-bem-network'
Requires-Dist: streamlit>=1.51.0; extra == 'sim-bem-network'
Provides-Extra: sim-chat-demo
Requires-Dist: streamlit>=1.51.0; extra == 'sim-chat-demo'
Provides-Extra: sim-chat-stream-demo
Requires-Dist: streamlit>=1.51.0; extra == 'sim-chat-stream-demo'
